NameExtractor/__init__.py
NameExtractor/downloaded.py
NameExtractor/names.py
NameExtractor/sslcert.py
NameExtractor-1.0.4.dist-info/METADATA
NameExtractor-1.0.4.dist-info/WHEEL
NameExtractor-1.0.4.dist-info/dependency_links.txt
NameExtractor-1.0.4.dist-info/top_level.txt
NameExtractor-1.0.4.dist-info/RECORD
