Metadata-Version: 2.1
Name: NameExtractor
Version: 1.0.4
Summary: Name Extractor is a small AI program to extract name and gender from characters in text.
Home-page: https://github.com/xDefyingGravity/Name-Extractor/
Author: Defying Gravity
License: UNKNOWN
Platform: UNKNOWN
Requires-Dist: nltk
Requires-Dist: spacy
